rustimport/__init__.py
rustimport/__main__.py
rustimport/checksum.py
rustimport/compiler.py
rustimport/error_handling.py
rustimport/find.py
rustimport/import_hook.py
rustimport/importable.py
rustimport/ipython_magic.py
rustimport/load.py
rustimport/py.typed
rustimport/settings.py
rustimport/pre_processing/__init__.py
rustimport/pre_processing/base.py
rustimport/pre_processing/pyo3_template.py
rustimport-1.7.1.dist-info/licenses/LICENSE
rustimport-1.7.1.dist-info/METADATA
rustimport-1.7.1.dist-info/WHEEL
rustimport-1.7.1.dist-info/top_level.txt
rustimport-1.7.1.dist-info/RECORD
